primerJinn/PCRinSilico.py
primerJinn/__init__.py
primerJinn/getMultiPrimerSet.py
primerJinn/primerJinn.py
primerjinn-2.0.3.dist-info/METADATA
primerjinn-2.0.3.dist-info/WHEEL
primerjinn-2.0.3.dist-info/entry_points.txt
primerjinn-2.0.3.dist-info/top_level.txt
primerjinn-2.0.3.dist-info/RECORD
