Metadata-Version: 2.4
Name: primerJinn
Version: 2.0.3
Summary: In silico PCR tool
Home-page: https://github.com/SemiQuant/primerJinn
Author: Jason D Limberis
Author-email: Jason.Limberis@ucsf.edu
License: GPL
Keywords: PCR,in silico PCR
Classifier: Programming Language :: Python :: 3
Classifier: License :: OSI Approved :: GNU General Public License v3 (GPLv3)
Classifier: Operating System :: OS Independent
Requires-Dist: scipy
Requires-Dist: pandas
Requires-Dist: biopython
Requires-Dist: numpy
Requires-Dist: primer3-py==2.0.3
Requires-Dist: networkx
Requires-Dist: scikit-learn
Requires-Dist: requests
Requires-Dist: openpyxl
Requires-Dist: matplotlib
Requires-Dist: tabulate
Dynamic: author
Dynamic: author-email
Dynamic: classifier
Dynamic: description
Dynamic: description-content-type
Dynamic: home-page
Dynamic: keywords
Dynamic: license
Dynamic: requires-dist
Dynamic: summary
